{
  "ambientocclusion": false,
  "textures": {
    "crop": "some_assembly_required:block/lettuce_stage0",
    "particle": "some_assembly_required:item/lettuce_head"
  },
  "elements": [
    {
      "from": [
        16,
        -1,
        8
      ],
      "to": [
        0,
        7,
        8
      ],
      "rotation": {
        "origin": [
          8,
          -1,
          8
        ],
        "axis": "x",
        "angle": -45.0
      },
      "shade": false,
      "faces": {
        "north": {
          "texture": "#crop",
          "uv": [
            0.0,
            0.0,
            8.0,
            4.0
          ]
        },
        "south": {
          "texture": "#crop",
          "uv": [
            0.0,
            4.0,
            8.0,
            8.0
          ]
        }
      }
    },
    {
      "from": [
        8,
        -1,
        16
      ],
      "to": [
        8,
        7,
        0
      ],
      "rotation": {
        "origin": [
          8,
          -1,
          8
        ],
        "axis": "z",
        "angle": 45.0
      },
      "shade": false,
      "faces": {
        "west": {
          "texture": "#crop",
          "uv": [
            0.0,
            0.0,
            8.0,
            4.0
          ]
        },
        "east": {
          "texture": "#crop",
          "uv": [
            0.0,
            4.0,
            8.0,
            8.0
          ]
        }
      }
    },
    {
      "from": [
        0,
        -1,
        8
      ],
      "to": [
        16,
        7,
        8
      ],
      "rotation": {
        "origin": [
          8,
          -1,
          8
        ],
        "axis": "x",
        "angle": 45.0
      },
      "shade": false,
      "faces": {
        "north": {
          "texture": "#crop",
          "uv": [
            0.0,
            0.0,
            8.0,
            4.0
          ]
        },
        "south": {
          "texture": "#crop",
          "uv": [
            0.0,
            4.0,
            8.0,
            8.0
          ]
        }
      }
    },
    {
      "from": [
        8,
        -1,
        0
      ],
      "to": [
        8,
        7,
        16
      ],
      "rotation": {
        "origin": [
          8,
          -1,
          8
        ],
        "axis": "z",
        "angle": -45.0
      },
      "shade": false,
      "faces": {
        "west": {
          "texture": "#crop",
          "uv": [
            0.0,
            0.0,
            8.0,
            4.0
          ]
        },
        "east": {
          "texture": "#crop",
          "uv": [
            0.0,
            4.0,
            8.0,
            8.0
          ]
        }
      }
    }
  ]
}